funciones/figuras.py
funciones/número.py
funciones/primos.py
funciones/tabla.py
funciones/texto.py
asix_Tofik_Varo-0.0.1.dist-info/METADATA
asix_Tofik_Varo-0.0.1.dist-info/WHEEL
asix_Tofik_Varo-0.0.1.dist-info/top_level.txt
asix_Tofik_Varo-0.0.1.dist-info/RECORD
