Metadata-Version: 2.1
Name: asix-Tofik-Varo
Version: 0.0.1
Summary: Ejemplo de como crear un paquete
Author-email: Tofik <onlyps3buys@gmail.com>
Project-URL: Homepage, https://github.com/levisman217/python
Project-URL: Bug Tracker, https://github.com/levisman217/python/issues
Classifier: Programming Language :: Python :: 3
Classifier: License :: OSI Approved :: MIT License
Classifier: Operating System :: OS Independent
Requires-Python: >=3.7
